indelible_log/__init__.py
indelible_log/crypto.py
indelible_log-0.4.6.dist-info/LICENSE.txt
indelible_log-0.4.6.dist-info/METADATA
indelible_log-0.4.6.dist-info/WHEEL
indelible_log-0.4.6.dist-info/top_level.txt
indelible_log-0.4.6.dist-info/RECORD
