Metadata-Version: 2.1
Name: indelible-log
Version: 0.4.6
Summary: client for Indelible managed persistent store and synchronizer
Home-page: https://indelible.systems
Author: Jeff Rhyason
Author-email: jeff@indelible.systems
License: MIT
Platform: UNKNOWN
Classifier: Programming Language :: Python :: 2.7
Classifier: Programming Language :: Python :: 3
Classifier: Development Status :: 4 - Beta
Classifier: Topic :: Database
Classifier: Intended Audience :: Developers
Classifier: Intended Audience :: System Administrators
Classifier: License :: OSI Approved :: MIT License
Classifier: Operating System :: OS Independent
Requires-Python: >=2.7, !=3.0.*, !=3.1.*, !=3.2.*, !=3.3.*, !=3.4.*, <4
Requires-Dist: requests
Requires-Dist: pynacl
